mcuser/__init__.py
mcuser/get.py
mcuser/module1.py
mcuser/module2.py
mcuser-1.0.2.dist-info/METADATA
mcuser-1.0.2.dist-info/WHEEL
mcuser-1.0.2.dist-info/top_level.txt
mcuser-1.0.2.dist-info/RECORD
