Metadata-Version: 2.1
Name: mcuser
Version: 1.0.2
Summary: parsing for Minecraft User Data module
Home-page: https://github.com/8954sood/mcuser
Author: babihoba
Author-email: hobabot@gmail.com
License: MIT
Platform: UNKNOWN
Classifier: Programming Language :: Python :: 3.8
Classifier: License :: OSI Approved :: MIT License
Classifier: Operating System :: OS Independent
